<?xml version = '1.0' encoding = 'UTF-8'?>
<Diagram class="oracle.dbtools.crest.swingui.relational.DPVRelational" name="Restaurant" id="7A763EBF-0E4A-B469-F3BE-21FAAADC4DFF">
<createdBy>Mike</createdBy>
<modifiedBy>Mike</modifiedBy>
<createdTime>2016-10-12 16:14:13 UTC</createdTime>
<autoRoute>false</autoRoute>
<boxInbox>true</boxInbox>
<showLegend>false</showLegend>
<showLabels>false</showLabels>
<showRelAttributes>false</showRelAttributes>
<gridEnabled>false</gridEnabled>
<showGrid>false</showGrid>
<diagramColor>-1</diagramColor>
<display>false</display>
<notation>1</notation>
<objectViews>
<OView class="oracle.dbtools.crest.swingui.relational.TVTable" oid="200CF4CB-838D-D336-DACF-BE57B3D2552B" otype="Table" vid="03F0CE2C-02D4-E125-F94E-D02BB571E3F0">
<hideElementsInCurrentOnly>false</hideElementsInCurrentOnly>
<bounds x="276" y="1032" width="212" height="156"/>
</OView>
<OView class="oracle.dbtools.crest.swingui.relational.TVTable" oid="2A688960-19BB-6C51-4BEC-FD2DCC891760" otype="Table" vid="86333EA5-32DA-8AD1-2B45-5BA967999CCB">
<hideElementsInCurrentOnly>false</hideElementsInCurrentOnly>
<bounds x="276" y="844" width="244" height="148"/>
</OView>
<OView class="oracle.dbtools.crest.swingui.relational.TVTable" oid="554DB3B1-4DBB-6CDA-2C03-2777B45C7A31" otype="Table" vid="CFDD4205-21BD-7B3D-B84B-41B2AFA79855">
<hideElementsInCurrentOnly>false</hideElementsInCurrentOnly>
<bounds x="275" y="1265" width="176" height="156"/>
</OView>
<OView class="oracle.dbtools.crest.swingui.relational.TVTable" oid="5F83F9E4-4700-9569-2189-351E524827A2" otype="Table" vid="F531B7D9-16BE-7311-92E8-471A0AD414E4">
<hideElementsInCurrentOnly>false</hideElementsInCurrentOnly>
<bounds x="438" y="634" width="200" height="150"/>
</OView>
<OView class="oracle.dbtools.crest.swingui.relational.TVTable" oid="71C77D15-DB99-A070-DD78-2A17F3FB0230" otype="Table" vid="AD13EAA4-55E9-AC1C-A42A-8020EBFCD9EC">
<hideElementsInCurrentOnly>false</hideElementsInCurrentOnly>
<bounds x="594" y="20" width="208" height="170"/>
</OView>
<OView class="oracle.dbtools.crest.swingui.relational.TVTable" oid="89274256-F40B-D1B0-4E28-8449BD8EEFDC" otype="Table" vid="14E5B9E2-822D-3F7F-956B-8D5E52216400">
<hideElementsInCurrentOnly>false</hideElementsInCurrentOnly>
<bounds x="594" y="250" width="224" height="122"/>
</OView>
<OView class="oracle.dbtools.crest.swingui.relational.TVTable" oid="9E6DEE06-355E-8936-CB52-12151AEC8ECF" otype="Table" vid="F01CBB47-A683-71D7-B4D0-0FF65C6E9E87">
<hideElementsInCurrentOnly>false</hideElementsInCurrentOnly>
<bounds x="438" y="432" width="232" height="142"/>
</OView>
<OView class="oracle.dbtools.crest.swingui.relational.TVTable" oid="A8009185-8F56-108B-7602-09961D69B184" otype="Table" vid="6E80C98D-FB32-69B3-D885-33878B23309D">
<hideElementsInCurrentOnly>false</hideElementsInCurrentOnly>
<bounds x="320" y="22" width="202" height="122"/>
</OView>
<OView class="oracle.dbtools.crest.swingui.relational.TVTable" oid="B4EA7F23-8FF1-60C0-2DB2-5BC935D1980D" otype="Table" vid="E80579FF-FC21-E70F-7C5A-86819525A49C">
<hideElementsInCurrentOnly>false</hideElementsInCurrentOnly>
<bounds x="750" y="432" width="270" height="142"/>
</OView>
<OView class="oracle.dbtools.crest.swingui.relational.TVTable" oid="C168ED93-81FC-6008-A303-3C35192C3C0E" otype="Table" vid="0293C760-2F64-27BF-C363-476C98838682">
<hideElementsInCurrentOnly>false</hideElementsInCurrentOnly>
<bounds x="882" y="20" width="183" height="136"/>
</OView>
<OView class="oracle.dbtools.crest.swingui.relational.TVTable" oid="CBCBB8A4-F504-3E57-D816-2C20BE293781" otype="Table" vid="D627505A-2139-2947-B454-CADC7D070CFC">
<hideElementsInCurrentOnly>false</hideElementsInCurrentOnly>
<bounds x="589" y="1053" width="183" height="108"/>
</OView>
<OView class="oracle.dbtools.crest.swingui.relational.TVTable" oid="F0D10283-A870-3A1E-D1C2-4680AB912946" otype="Table" vid="EB7C614C-D88C-846A-AA31-F22E4A8F0D4C">
<hideElementsInCurrentOnly>false</hideElementsInCurrentOnly>
<bounds x="600" y="844" width="174" height="142"/>
</OView>
</objectViews>
<connectors>
<Connector class="oracle.dbtools.crest.swingui.relational.TVFKRelation" oid="53FA41C0-A4D7-9D12-1119-FBB2CE390666" otype="FKIndexAssociation" vid_source="03F0CE2C-02D4-E125-F94E-D02BB571E3F0" vid_target="CFDD4205-21BD-7B3D-B84B-41B2AFA79855">
<hideElementsInCurrentOnly>false</hideElementsInCurrentOnly>
<lineWidth>1</lineWidth>
<points>
<point x="363" y="1188"/>
<point x="363" y="1265"/>
</points>
</Connector>
<Connector class="oracle.dbtools.crest.swingui.relational.TVFKRelation" oid="63128B6C-DF25-4E7D-0D15-61F7E83EBEBA" otype="FKIndexAssociation" vid_source="F531B7D9-16BE-7311-92E8-471A0AD414E4" vid_target="EB7C614C-D88C-846A-AA31-F22E4A8F0D4C">
<hideElementsInCurrentOnly>false</hideElementsInCurrentOnly>
<lineWidth>1</lineWidth>
<points>
<point x="619" y="784"/>
<point x="619" y="844"/>
</points>
</Connector>
<Connector class="oracle.dbtools.crest.swingui.relational.TVFKRelation" oid="6E0D82E7-8BAD-FAEF-904E-C0536BD60CA1" otype="FKIndexAssociation" vid_source="14E5B9E2-822D-3F7F-956B-8D5E52216400" vid_target="F01CBB47-A683-71D7-B4D0-0FF65C6E9E87">
<hideElementsInCurrentOnly>false</hideElementsInCurrentOnly>
<lineWidth>1</lineWidth>
<points>
<point x="632" y="372"/>
<point x="632" y="432"/>
</points>
</Connector>
<Connector class="oracle.dbtools.crest.swingui.relational.TVFKRelation" oid="716A4FE1-1926-1E84-30F9-F74B18AC8E1E" otype="FKIndexAssociation" vid_source="0293C760-2F64-27BF-C363-476C98838682" vid_target="AD13EAA4-55E9-AC1C-A42A-8020EBFCD9EC">
<hideElementsInCurrentOnly>false</hideElementsInCurrentOnly>
<lineWidth>1</lineWidth>
<points>
<point x="882" y="88"/>
<point x="802" y="88"/>
</points>
</Connector>
<Connector class="oracle.dbtools.crest.swingui.relational.TVFKRelation" oid="7B11AB87-C70E-8754-A5CA-461D1F96B87A" otype="FKIndexAssociation" vid_source="14E5B9E2-822D-3F7F-956B-8D5E52216400" vid_target="AD13EAA4-55E9-AC1C-A42A-8020EBFCD9EC">
<hideElementsInCurrentOnly>false</hideElementsInCurrentOnly>
<lineWidth>1</lineWidth>
<points>
<point x="698" y="250"/>
<point x="698" y="190"/>
</points>
</Connector>
<Connector class="oracle.dbtools.crest.swingui.relational.TVFKRelation" oid="9E528A08-0296-C7B8-E42E-1432A5FB1799" otype="FKIndexAssociation" vid_source="14E5B9E2-822D-3F7F-956B-8D5E52216400" vid_target="E80579FF-FC21-E70F-7C5A-86819525A49C">
<hideElementsInCurrentOnly>false</hideElementsInCurrentOnly>
<lineWidth>1</lineWidth>
<points>
<point x="774" y="372"/>
<point x="774" y="432"/>
</points>
</Connector>
<Connector class="oracle.dbtools.crest.swingui.relational.TVFKRelation" oid="A4F59378-9670-3784-F45B-E72A553718C3" otype="FKIndexAssociation" vid_source="03F0CE2C-02D4-E125-F94E-D02BB571E3F0" vid_target="86333EA5-32DA-8AD1-2B45-5BA967999CCB">
<hideElementsInCurrentOnly>false</hideElementsInCurrentOnly>
<lineWidth>1</lineWidth>
<points>
<point x="382" y="1032"/>
<point x="382" y="992"/>
</points>
</Connector>
<Connector class="oracle.dbtools.crest.swingui.relational.TVFKRelation" oid="B2E965E5-D59F-3EDC-87A6-7569DC6398CD" otype="FKIndexAssociation" vid_source="F531B7D9-16BE-7311-92E8-471A0AD414E4" vid_target="86333EA5-32DA-8AD1-2B45-5BA967999CCB">
<hideElementsInCurrentOnly>false</hideElementsInCurrentOnly>
<lineWidth>1</lineWidth>
<points>
<point x="479" y="784"/>
<point x="479" y="844"/>
</points>
</Connector>
<Connector class="oracle.dbtools.crest.swingui.relational.TVFKRelation" oid="BEE92239-1D03-D1DA-E256-D8405198992F" otype="FKIndexAssociation" vid_source="F531B7D9-16BE-7311-92E8-471A0AD414E4" vid_target="F01CBB47-A683-71D7-B4D0-0FF65C6E9E87">
<hideElementsInCurrentOnly>false</hideElementsInCurrentOnly>
<lineWidth>1</lineWidth>
<points>
<point x="538" y="634"/>
<point x="538" y="574"/>
</points>
</Connector>
<Connector class="oracle.dbtools.crest.swingui.relational.TVFKRelation" oid="F443CF26-6754-B6A5-3682-F71F370F2891" otype="FKIndexAssociation" vid_source="D627505A-2139-2947-B454-CADC7D070CFC" vid_target="03F0CE2C-02D4-E125-F94E-D02BB571E3F0">
<hideElementsInCurrentOnly>false</hideElementsInCurrentOnly>
<lineWidth>1</lineWidth>
<points>
<point x="589" y="1107"/>
<point x="488" y="1107"/>
</points>
</Connector>
</connectors>
</Diagram>