<?xml version = '1.0' encoding = 'UTF-8'?>
<TableProxyOraclev12c class="oracle.dbtools.crest.model.design.storage.oracle.v12c.TableProxyOraclev12c" name="RESOURCES" directorySegmentName="seg_0" id="A8009185-8F56-108B-7602-09961D69B184">
<createdBy>Mike</createdBy>
<createdTime>2016-10-12 16:14:13 UTC</createdTime>
<ownerDesignName>RestaurantDataModel</ownerDesignName>
<partitionedRowMovement>DISABLE</partitionedRowMovement>
<temporaryChanged>false</temporaryChanged>
<accessDriverType>oracle_loader</accessDriverType>
<rejectLimit></rejectLimit>
<columnProxies itemClass="oracle.dbtools.crest.model.design.storage.oracle.v12c.ColumnProxyOraclev12c">
<ColumnProxy name="Type" id="712DAD9F-9E1C-8B97-7540-5125D3A03C18">
<createdBy>Mike</createdBy>
<createdTime>2016-10-12 16:14:13 UTC</createdTime>
<ownerDesignName>RestaurantDataModel</ownerDesignName>
</ColumnProxy>
<ColumnProxy name="ResourceID" id="97E7B8C9-F1B5-0253-447D-2AF5E3F13B89">
<createdBy>Mike</createdBy>
<createdTime>2016-10-12 16:14:13 UTC</createdTime>
<ownerDesignName>RestaurantDataModel</ownerDesignName>
</ColumnProxy>
<ColumnProxy name="Total" id="A5E31E1D-5C7E-81E1-49B2-71A270E441E7">
<createdBy>Mike</createdBy>
<createdTime>2016-10-12 16:14:13 UTC</createdTime>
<ownerDesignName>RestaurantDataModel</ownerDesignName>
</ColumnProxy>
<ColumnProxy name="DateReceived" id="B10B8E6F-207D-A006-29AF-25B8F6BF56F3">
<createdBy>Mike</createdBy>
<createdTime>2016-10-12 16:14:13 UTC</createdTime>
<ownerDesignName>RestaurantDataModel</ownerDesignName>
</ColumnProxy>
</columnProxies>
<indexProxies>
<IndexProxy class="oracle.dbtools.crest.model.design.storage.oracle.v10g.IndexProxyOraclev10g" name="XPKRESOURCES" id="CC495CE9-7D70-3881-9327-C3011A051F29">
<createdBy>Mike</createdBy>
<createdTime>2016-10-12 16:14:13 UTC</createdTime>
<ownerDesignName>RestaurantDataModel</ownerDesignName>
<logging></logging>
</IndexProxy>
</indexProxies>
<primaryKeys>
<PrimaryKey class="oracle.dbtools.crest.model.design.storage.oracle.v10g.PKProxyOraclev10g" name="XPKRESOURCES" id="80F0BC2C-B3B5-0512-C19D-1BEDC96D47FD">
<createdBy>Mike</createdBy>
<createdTime>2016-10-12 16:14:13 UTC</createdTime>
<ownerDesignName>RestaurantDataModel</ownerDesignName>
<indexSort>SORTED</indexSort>
</PrimaryKey>
</primaryKeys>
</TableProxyOraclev12c>